Metadata-Version: 2.1
Name: basicutilspackage
Version: 0.0.1
Summary: A very basic packages
Home-page: 
Author: pbl6-group2
Author-email: joblink.pbl6@gmail.com
License: MIT
Keywords: utils
Classifier: Development Status :: 5 - Production/Stable
Classifier: Intended Audience :: Education
Classifier: Operating System :: Microsoft :: Windows :: Windows 10
Classifier: License :: OSI Approved :: MIT License
Classifier: Programming Language :: Python :: 3
License-File: LICENCE.txt
